cifar10/__init__.py
cifar10/cifar10.py
cifar10/download.py
cifar10-1.0.0.dist-info/LICENSE
cifar10-1.0.0.dist-info/METADATA
cifar10-1.0.0.dist-info/WHEEL
cifar10-1.0.0.dist-info/top_level.txt
cifar10-1.0.0.dist-info/RECORD
