Metadata-Version: 2.1
Name: cifar10
Version: 1.0.0
Summary: UNKNOWN
Home-page: https://github.com/joeyism/cifar10
Author: joeyism
Author-email: joeyism@gmail.com
License: UNKNOWN
Download-URL: https://github.com/joeyism/cifar10/archive/1.0.0.tar.gz
Keywords: cifar,cifar10,ten,10,machine,learning,database
Platform: UNKNOWN
Requires-Dist: requests
Requires-Dist: tqdm
Requires-Dist: numpy
